devqubit_cirq/__init__.py
devqubit_cirq/adapter.py
devqubit_cirq/circuits.py
devqubit_cirq/py.typed
devqubit_cirq/results.py
devqubit_cirq/serialization.py
devqubit_cirq/snapshot.py
devqubit_cirq/utils.py
devqubit_cirq-0.1.10.dist-info/METADATA
devqubit_cirq-0.1.10.dist-info/WHEEL
devqubit_cirq-0.1.10.dist-info/entry_points.txt
devqubit_cirq-0.1.10.dist-info/licenses/LICENSE
devqubit_cirq-0.1.10.dist-info/RECORD
