Metadata-Version: 2.4
Name: devqubit-cirq
Version: 0.1.10
Summary: devqubit adapter for Cirq
Author: devqubit
License-Expression: Apache-2.0
License-File: LICENSE
Keywords: cirq,experiment-tracking,quantum
Classifier: Development Status :: 3 - Alpha
Classifier: License :: OSI Approved :: Apache Software License
Classifier: Operating System :: OS Independent
Classifier: Programming Language :: Python :: 3
Classifier: Programming Language :: Python :: 3 :: Only
Classifier: Programming Language :: Python :: 3.11
Classifier: Programming Language :: Python :: 3.12
Classifier: Programming Language :: Python :: 3.13
Requires-Python: <3.14,>=3.11
Requires-Dist: cirq<2,>=1.6
Requires-Dist: devqubit-engine<0.2.0,>=0.1.10
Requires-Dist: ply>=3.11
